.gitignore
.gitlab-ci.yml
.project.vim
.skel.py
.travis.yml
CONTRIBUTING.rst
LICENSE
MANIFEST.in
README.rst
setup.py
tox.ini
appi/__init__.py
appi/atom.py
appi/ebuild.py
appi/exception.py
appi/util.py
appi/version.py
appi.egg-info/PKG-INFO
appi.egg-info/SOURCES.txt
appi.egg-info/dependency_links.txt
appi.egg-info/top_level.txt
appi/base/__init__.py
appi/base/constant.py
appi/base/exception.py
appi/base/mixin.py
appi/base/util/__init__.py
appi/base/util/decorator.py
appi/conf/__init__.py
appi/conf/base.py
appi/conf/profile.py
appi/conf/repository.py
docs/Makefile
docs/conf.py
docs/getstarted.rst
docs/index.rst
docs/install.rst
docs/_static/.keep
docs/ref/index.rst
docs/ref/appi/DependAtom.rst
docs/ref/appi/Ebuild.rst
docs/ref/appi/QueryAtom.rst
docs/ref/appi/Version.rst
docs/ref/appi/index.rst
docs/ref/appi/conf/Profile.rst
docs/ref/appi/conf/Repository.rst
docs/ref/appi/conf/index.rst
docs/ref/appi/exception/AppiError.rst
docs/ref/appi/exception/AtomError.rst
docs/ref/appi/exception/EbuildError.rst
docs/ref/appi/exception/PortageError.rst
docs/ref/appi/exception/VersionError.rst
docs/ref/appi/exception/index.rst
requirements/base.txt
requirements/extra-docs-theme.txt
requirements/extra-docs.txt
test/test_atom.py
test/test_ebuild.py
test/test_version.py