Metadata-Version: 2.1
Name: appi
Version: 0.2.4
Summary: This is a python module created by Antoine Pinsard that powers ego query commands.
Home-page: https://code.funtoo.org/bitbucket/projects/CORE/repos/appi/browse
Author: Daniel Robbins, Antoine Pinsard
Author-email: drobbins@funtoo.org
License: UNKNOWN
Platform: UNKNOWN
Classifier: Programming Language :: Python :: 3
Classifier: License :: OSI Approved :: GNU General Public License v2 (GPLv2)
Classifier: Operating System :: POSIX :: Linux
Requires-Python: >=3.7
